cmdrdata/__init__.py
cmdrdata/client.py
cmdrdata/context.py
cmdrdata/exceptions.py
cmdrdata/py.typed
cmdrdata/tracker.py
cmdrdata-0.1.0.dist-info/licenses/LICENSE
cmdrdata-0.1.0.dist-info/METADATA
cmdrdata-0.1.0.dist-info/WHEEL
cmdrdata-0.1.0.dist-info/top_level.txt
cmdrdata-0.1.0.dist-info/RECORD
